diffusers/__init__.py
diffusers/callbacks.py
diffusers/configuration_utils.py
diffusers/dependency_versions_check.py
diffusers/dependency_versions_table.py
diffusers/image_processor.py
diffusers/optimization.py
diffusers/py.typed
diffusers/training_utils.py
diffusers/video_processor.py
diffusers/commands/__init__.py
diffusers/commands/custom_blocks.py
diffusers/commands/diffusers_cli.py
diffusers/commands/env.py
diffusers/commands/fp16_safetensors.py
diffusers/experimental/__init__.py
diffusers/experimental/rl/__init__.py
diffusers/experimental/rl/value_guided_sampling.py
diffusers/guiders/__init__.py
diffusers/guiders/adaptive_projected_guidance.py
diffusers/guiders/auto_guidance.py
diffusers/guiders/classifier_free_guidance.py
diffusers/guiders/classifier_free_zero_star_guidance.py
diffusers/guiders/frequency_decoupled_guidance.py
diffusers/guiders/guider_utils.py
diffusers/guiders/perturbed_attention_guidance.py
diffusers/guiders/skip_layer_guidance.py
diffusers/guiders/smoothed_energy_guidance.py
diffusers/guiders/tangential_classifier_free_guidance.py
diffusers/hooks/__init__.py
diffusers/hooks/_common.py
diffusers/hooks/_helpers.py
diffusers/hooks/faster_cache.py
diffusers/hooks/first_block_cache.py
diffusers/hooks/group_offloading.py
diffusers/hooks/hooks.py
diffusers/hooks/layer_skip.py
diffusers/hooks/layerwise_casting.py
diffusers/hooks/pyramid_attention_broadcast.py
diffusers/hooks/smoothed_energy_guidance_utils.py
diffusers/hooks/utils.py
diffusers/loaders/__init__.py
diffusers/loaders/ip_adapter.py
diffusers/loaders/lora_base.py
diffusers/loaders/lora_conversion_utils.py
diffusers/loaders/lora_pipeline.py
diffusers/loaders/peft.py
diffusers/loaders/single_file.py
diffusers/loaders/single_file_model.py
diffusers/loaders/single_file_utils.py
diffusers/loaders/textual_inversion.py
diffusers/loaders/transformer_flux.py
diffusers/loaders/transformer_sd3.py
diffusers/loaders/unet.py
diffusers/loaders/unet_loader_utils.py
diffusers/loaders/utils.py
my_diffusers-0.36.0.dev0.dist-info/licenses/LICENSE
my_diffusers-0.36.0.dev0.dist-info/METADATA
my_diffusers-0.36.0.dev0.dist-info/WHEEL
my_diffusers-0.36.0.dev0.dist-info/entry_points.txt
my_diffusers-0.36.0.dev0.dist-info/top_level.txt
my_diffusers-0.36.0.dev0.dist-info/RECORD
