Metadata-Version: 2.4
Name: my_diffusers
Version: 0.36.0.dev0
Summary: State-of-the-art diffusion in PyTorch and JAX.
Home-page: https://github.com/huggingface/diffusers
Author: The Hugging Face team (past and future) with the help of all our contributors (https://github.com/huggingface/diffusers/graphs/contributors)
Author-email: diffusers@huggingface.co
License: Apache 2.0 License
Keywords: deep learning diffusion jax pytorch stable diffusion audioldm
Classifier: Development Status :: 5 - Production/Stable
Classifier: Intended Audience :: Developers
Classifier: Intended Audience :: Education
Classifier: Intended Audience :: Science/Research
Classifier: License :: OSI Approved :: Apache Software License
Classifier: Operating System :: OS Independent
Classifier: Topic :: Scientific/Engineering :: Artificial Intelligence
Classifier: Programming Language :: Python :: 3
Classifier: Programming Language :: Python :: 3.8
Classifier: Programming Language :: Python :: 3.9
Classifier: Programming Language :: Python :: 3.10
Classifier: Programming Language :: Python :: 3.11
Classifier: Programming Language :: Python :: 3.12
Requires-Python: >=3.8.0
License-File: LICENSE
Requires-Dist: importlib_metadata
Requires-Dist: filelock
Requires-Dist: huggingface-hub>=0.34.0
Requires-Dist: numpy
Requires-Dist: regex!=2019.12.17
Requires-Dist: requests
Requires-Dist: safetensors>=0.3.1
Requires-Dist: Pillow
Provides-Extra: quality
Requires-Dist: urllib3<=2.0.0; extra == "quality"
Requires-Dist: isort>=5.5.4; extra == "quality"
Requires-Dist: ruff==0.9.10; extra == "quality"
Requires-Dist: hf-doc-builder>=0.3.0; extra == "quality"
Provides-Extra: docs
Requires-Dist: hf-doc-builder>=0.3.0; extra == "docs"
Provides-Extra: training
Requires-Dist: accelerate>=0.31.0; extra == "training"
Requires-Dist: datasets; extra == "training"
Requires-Dist: protobuf<4,>=3.20.3; extra == "training"
Requires-Dist: tensorboard; extra == "training"
Requires-Dist: Jinja2; extra == "training"
Requires-Dist: peft>=0.17.0; extra == "training"
Provides-Extra: test
Requires-Dist: compel==0.1.8; extra == "test"
Requires-Dist: GitPython<3.1.19; extra == "test"
Requires-Dist: datasets; extra == "test"
Requires-Dist: Jinja2; extra == "test"
Requires-Dist: invisible-watermark>=0.2.0; extra == "test"
Requires-Dist: k-diffusion==0.0.12; extra == "test"
Requires-Dist: librosa; extra == "test"
Requires-Dist: parameterized; extra == "test"
Requires-Dist: pytest; extra == "test"
Requires-Dist: pytest-timeout; extra == "test"
Requires-Dist: pytest-xdist; extra == "test"
Requires-Dist: requests-mock==1.10.0; extra == "test"
Requires-Dist: safetensors>=0.3.1; extra == "test"
Requires-Dist: sentencepiece!=0.1.92,>=0.1.91; extra == "test"
Requires-Dist: scipy; extra == "test"
Requires-Dist: tiktoken>=0.7.0; extra == "test"
Requires-Dist: torchvision; extra == "test"
Requires-Dist: transformers>=4.41.2; extra == "test"
Requires-Dist: phonemizer; extra == "test"
Provides-Extra: torch
Requires-Dist: torch>=1.4; extra == "torch"
Requires-Dist: accelerate>=0.31.0; extra == "torch"
Provides-Extra: bitsandbytes
Requires-Dist: bitsandbytes>=0.43.3; extra == "bitsandbytes"
Requires-Dist: accelerate>=0.31.0; extra == "bitsandbytes"
Provides-Extra: gguf
Requires-Dist: gguf>=0.10.0; extra == "gguf"
Requires-Dist: accelerate>=0.31.0; extra == "gguf"
Provides-Extra: optimum-quanto
Requires-Dist: optimum_quanto>=0.2.6; extra == "optimum-quanto"
Requires-Dist: accelerate>=0.31.0; extra == "optimum-quanto"
Provides-Extra: torchao
Requires-Dist: torchao>=0.7.0; extra == "torchao"
Requires-Dist: accelerate>=0.31.0; extra == "torchao"
Provides-Extra: flax
Requires-Dist: jax>=0.4.1; extra == "flax"
Requires-Dist: jaxlib>=0.4.1; extra == "flax"
Requires-Dist: flax>=0.4.1; extra == "flax"
Provides-Extra: dev
Requires-Dist: urllib3<=2.0.0; extra == "dev"
Requires-Dist: isort>=5.5.4; extra == "dev"
Requires-Dist: ruff==0.9.10; extra == "dev"
Requires-Dist: hf-doc-builder>=0.3.0; extra == "dev"
Requires-Dist: compel==0.1.8; extra == "dev"
Requires-Dist: GitPython<3.1.19; extra == "dev"
Requires-Dist: datasets; extra == "dev"
Requires-Dist: Jinja2; extra == "dev"
Requires-Dist: invisible-watermark>=0.2.0; extra == "dev"
Requires-Dist: k-diffusion==0.0.12; extra == "dev"
Requires-Dist: librosa; extra == "dev"
Requires-Dist: parameterized; extra == "dev"
Requires-Dist: pytest; extra == "dev"
Requires-Dist: pytest-timeout; extra == "dev"
Requires-Dist: pytest-xdist; extra == "dev"
Requires-Dist: requests-mock==1.10.0; extra == "dev"
Requires-Dist: safetensors>=0.3.1; extra == "dev"
Requires-Dist: sentencepiece!=0.1.92,>=0.1.91; extra == "dev"
Requires-Dist: scipy; extra == "dev"
Requires-Dist: tiktoken>=0.7.0; extra == "dev"
Requires-Dist: torchvision; extra == "dev"
Requires-Dist: transformers>=4.41.2; extra == "dev"
Requires-Dist: phonemizer; extra == "dev"
Requires-Dist: accelerate>=0.31.0; extra == "dev"
Requires-Dist: datasets; extra == "dev"
Requires-Dist: protobuf<4,>=3.20.3; extra == "dev"
Requires-Dist: tensorboard; extra == "dev"
Requires-Dist: Jinja2; extra == "dev"
Requires-Dist: peft>=0.17.0; extra == "dev"
Requires-Dist: hf-doc-builder>=0.3.0; extra == "dev"
Requires-Dist: torch>=1.4; extra == "dev"
Requires-Dist: accelerate>=0.31.0; extra == "dev"
Requires-Dist: jax>=0.4.1; extra == "dev"
Requires-Dist: jaxlib>=0.4.1; extra == "dev"
Requires-Dist: flax>=0.4.1; extra == "dev"
Dynamic: author
Dynamic: author-email
Dynamic: classifier
Dynamic: description
Dynamic: description-content-type
Dynamic: home-page
Dynamic: keywords
Dynamic: license
Dynamic: license-file
Dynamic: provides-extra
Dynamic: requires-dist
Dynamic: requires-python
Dynamic: summary
